pullenti/__init__.py
pullenti/address/AddressHelper.py
pullenti/address/AddressRepository.py
pullenti/address/AddressService.py
pullenti/address/AreaAttributes.py
pullenti/address/BaseAttributes.py
pullenti/address/GarLevel.py
pullenti/address/GarObject.py
pullenti/address/GarParam.py
pullenti/address/GarStatistic.py
pullenti/address/HouseAttributes.py
pullenti/address/HouseType.py
pullenti/address/ImageWrapper.py
pullenti/address/RepaddrObject.py
pullenti/address/RoomAttributes.py
pullenti/address/RoomType.py
pullenti/address/SearchParams.py
pullenti/address/SearchResult.py
pullenti/address/SpecialAttributes.py
pullenti/address/SpecialType.py
pullenti/address/StroenType.py
pullenti/address/TextAddress.py
pullenti/address/TextObject.py
pullenti/address/__init__.py
pullenti/address/internal/AbbrTreeNode.py
pullenti/address/internal/AddrSearchFormal.py
pullenti/address/internal/AddressSearchHelper.py
pullenti/address/internal/AnalyzeHelper.py
pullenti/address/internal/CorrectionHelper.py
pullenti/address/internal/FiasHelper.py
pullenti/address/internal/GarHelper.py
pullenti/address/internal/NameAnalyzer.py
pullenti/address/internal/PullentiAddressInternalResourceHelper.py
pullenti/address/internal/RepAddrTree.py
pullenti/address/internal/RepAddrTreeNode.py
pullenti/address/internal/RepAddrTreeNodeObj.py
pullenti/address/internal/RepChildrenTable.py
pullenti/address/internal/RepObjTable.py
pullenti/address/internal/RepObjTree.py
pullenti/address/internal/RepObjTreeNode.py
pullenti/address/internal/RepTypTable.py
pullenti/address/internal/RepaddrSearchObj.py
pullenti/address/internal/SearchAddressItem.py
pullenti/address/internal/SearchLevel.py
pullenti/address/internal/ServerHelper.py
pullenti/address/internal/__init__.py
pullenti/address/internal/gar/ATreeNode.py
pullenti/address/internal/gar/ATreeRoot.py
pullenti/address/internal/gar/AddrInfo.py
pullenti/address/internal/gar/AddrTyp.py
pullenti/address/internal/gar/AddressObject.py
PullentiPython-0.1.dist-info/LICENSE.txt
PullentiPython-0.1.dist-info/METADATA
PullentiPython-0.1.dist-info/WHEEL
PullentiPython-0.1.dist-info/top_level.txt
PullentiPython-0.1.dist-info/RECORD
